color_notify.py
color_notify-1.0.10.dist-info/licenses/LICENSE
color_notify-1.0.10.dist-info/METADATA
color_notify-1.0.10.dist-info/WHEEL
color_notify-1.0.10.dist-info/entry_points.txt
color_notify-1.0.10.dist-info/top_level.txt
color_notify-1.0.10.dist-info/RECORD
