Metadata-Version: 2.4
Name: color-notify
Version: 1.0.10
Summary: Desktop notification tool for clipboard color code detection
Home-page: https://github.com/cumulus13/color-notify
Author: Hadi Cahyadi
Author-email: Hadi Cahyadi <cumulus13@gmail.com>
Maintainer-email: Hadi Cahyadi <cumulus13@gmail.com>
License: MIT
Project-URL: Homepage, https://github.com/cumulus13/color-notify
Project-URL: Documentation, https://github.com/cumulus13/color-notify#readme
Project-URL: Repository, https://github.com/cumulus13/color-notify
Project-URL: Bug Tracker, https://github.com/cumulus13/color-notify/issues
Project-URL: Changelog, https://github.com/cumulus13/color-notify/blob/main/CHANGELOG.md
Keywords: color,notification,clipboard,monitor,desktop,growl,hex,rgb,color-picker,system-tray,pyqt5,qt,gui
Classifier: Development Status :: 5 - Production/Stable
Classifier: Intended Audience :: Developers
Classifier: Intended Audience :: End Users/Desktop
Classifier: Topic :: Utilities
Classifier: Topic :: Desktop Environment
Classifier: Topic :: Software Development :: User Interfaces
Classifier: Programming Language :: Python :: 3
Classifier: Programming Language :: Python :: 3.6
Classifier: Programming Language :: Python :: 3.7
Classifier: Programming Language :: Python :: 3.8
Classifier: Programming Language :: Python :: 3.9
Classifier: Programming Language :: Python :: 3.10
Classifier: Programming Language :: Python :: 3.11
Classifier: Programming Language :: Python :: 3.12
Classifier: Operating System :: OS Independent
Classifier: Operating System :: Microsoft :: Windows
Classifier: Operating System :: POSIX :: Linux
Classifier: Operating System :: MacOS
Classifier: Environment :: X11 Applications :: Qt
Requires-Python: >=3.6
License-File: LICENSE
Requires-Dist: PyQt5>=5.15.0
Requires-Dist: pynput>=1.7.6
Requires-Dist: version_get
Dynamic: author
Dynamic: home-page
Dynamic: license-file
Dynamic: requires-python
